reprlearn/__init__.py
reprlearn/data/__init__.py
reprlearn/data/build.py
reprlearn/data/datamodules/__init__.py
reprlearn/data/datamodules/base_datamodule.py
reprlearn/data/datamodules/maptiles_datamodule.py
reprlearn/data/datamodules/mnist_datamodule.py
reprlearn/data/datamodules/mnistm_datamodule.py
reprlearn/data/datamodules/mono_mnist_datamodule.py
reprlearn/data/datamodules/multisource_datamodule.py
reprlearn/data/datamodules/multisource_maptiles_datamodule.py
reprlearn/data/datamodules/multisource_mono_mnist_datamodule.py
reprlearn/data/datamodules/multisource_osmnxr_datamodule.py
reprlearn/data/datamodules/multisource_rotated_mnist_datamodule.py
reprlearn/data/datamodules/rotated_mnist_datamodule.py
reprlearn/data/datamodules/usps_datamodule.py
reprlearn/data/datasets/__init__.py
reprlearn/data/datasets/faces.py
reprlearn/data/datasets/maptiles.py
reprlearn/data/datasets/maptiles_bifactor.py
reprlearn/data/datasets/mnist.py
reprlearn/data/datasets/mnistm.py
reprlearn/data/datasets/mono_mnist.py
reprlearn/data/datasets/multisource_mono_mnist.py
reprlearn/data/datasets/multisource_rotated_mnist.py
reprlearn/data/datasets/rotated_mnist.py
reprlearn/data/datasets/two_factor_dataset.py
reprlearn/data/datasets/utils.py
reprlearn/data/transforms/__init__.py
reprlearn/data/transforms/build.py
reprlearn/data/transforms/functional.py
reprlearn/data/transforms/transforms.py
reprlearn/models/__init__.py
reprlearn/models/bilinear.py
reprlearn/models/convnet.py
reprlearn/models/deep_bilinear.py
reprlearn/models/gmm.py
reprlearn/models/model_wrapper.py
reprlearn/models/resnet.py
reprlearn/models/resnet_deconv.py
reprlearn/models/sym_bilinear.py
reprlearn/models/types_.py
reprlearn/models/mackay/__init__.py
reprlearn/models/mackay/channels/__init__.py
reprlearn/models/mackay/channels/binary_sym_channel.py
reprlearn/models/mackay/decoders/__init__.py
reprlearn/models/mackay/decoders/rep_decoder.py
reprlearn/models/mackay/encoders/__init__.py
reprlearn-0.0.1.dist-info/LICENSE
reprlearn-0.0.1.dist-info/METADATA
reprlearn-0.0.1.dist-info/WHEEL
reprlearn-0.0.1.dist-info/top_level.txt
reprlearn-0.0.1.dist-info/RECORD
