Metadata-Version: 2.1
Name: reprlearn
Version: 0.0.1
Summary: A practice example package
Home-page: https://github.com/cocoaaa/ReprLearn
Author: Hayley Song
Author-email: haejinso@usc.edu
License: UNKNOWN
Platform: UNKNOWN
Requires-Python: >=3.6
License-File: LICENSE
